odoo/addons/selfconsumption_installation/CHANGELOG.md
odoo/addons/selfconsumption_installation/__init__.py
odoo/addons/selfconsumption_installation/__manifest__.py
odoo/addons/selfconsumption_installation/cliff.toml
odoo/addons/selfconsumption_installation/data/installation.role.csv
odoo/addons/selfconsumption_installation/data/res.partner.category.csv
odoo/addons/selfconsumption_installation/i18n/es.po
odoo/addons/selfconsumption_installation/i18n/selfconsumption_installation.pot
odoo/addons/selfconsumption_installation/models/__init__.py
odoo/addons/selfconsumption_installation/models/account_move.py
odoo/addons/selfconsumption_installation/models/installation_associated_supply.py
odoo/addons/selfconsumption_installation/models/installation_cover.py
odoo/addons/selfconsumption_installation/models/installation_electric_line.py
odoo/addons/selfconsumption_installation/models/installation_event.py
odoo/addons/selfconsumption_installation/models/installation_inverter.py
odoo/addons/selfconsumption_installation/models/installation_legal_requirement.py
odoo/addons/selfconsumption_installation/models/installation_module.py
odoo/addons/selfconsumption_installation/models/installation_role.py
odoo/addons/selfconsumption_installation/models/installation_role_line.py
odoo/addons/selfconsumption_installation/models/purchase_order.py
odoo/addons/selfconsumption_installation/models/res_config_settings.py
odoo/addons/selfconsumption_installation/models/res_partner.py
odoo/addons/selfconsumption_installation/models/sale_order.py
odoo/addons/selfconsumption_installation/models/selfconsumption_installation.py
odoo/addons/selfconsumption_installation/models/selfconsumption_installation_simulation.py
odoo/addons/selfconsumption_installation/security/ir.model.access.csv
odoo/addons/selfconsumption_installation/static/description/icon.png
odoo/addons/selfconsumption_installation/views/account_move_views.xml
odoo/addons/selfconsumption_installation/views/installation_event_views.xml
odoo13_addon_selfconsumption_installation-13.0.1.3.0.dist-info/METADATA
odoo13_addon_selfconsumption_installation-13.0.1.3.0.dist-info/WHEEL
odoo13_addon_selfconsumption_installation-13.0.1.3.0.dist-info/top_level.txt
odoo13_addon_selfconsumption_installation-13.0.1.3.0.dist-info/RECORD
